LICENSE.txt
MANIFEST.in
README.rst
dev_requirements.txt
requirements.txt
setup.cfg
setup.py
pycsync/__init__.py
pycsync/auth.py
pycsync/sync.py
pycsync/version.py
pycsync.egg-info/PKG-INFO
pycsync.egg-info/SOURCES.txt
pycsync.egg-info/dependency_links.txt
pycsync.egg-info/not-zip-safe
pycsync.egg-info/requires.txt
pycsync.egg-info/top_level.txt
scripts/pycsync