Metadata-Version: 1.1
Name: pycsync
Version: 0.1b1
Summary: Sync local photos with Flickr
Home-page: https://github.com/shadowfax-chc/pycsync
Author: Timothy F Messier
Author-email: tim.messier@gmail.com
License: ISC
Platform: UNKNOWN
Classifier: Programming Language :: Python
Classifier: Programming Language :: Python :: 2.7
Classifier: Development Status :: 4 - Beta
Classifier: Intended Audience :: Developers
Classifier: Intended Audience :: End Users/Desktop
Classifier: Environment :: Console
Classifier: License :: OSI Approved :: ISC License (ISCL)
Classifier: Operating System :: POSIX :: Linux
